brickbreaker/__init__.py
brickbreaker/__main__.py
brickbreaker/ball.py
brickbreaker/block.py
brickbreaker/game_manager.py
brickbreaker/hud.py
brickbreaker/level.py
brickbreaker/message.py
brickbreaker/object_definitions.py
brickbreaker/paddle.py
brickbreaker/scores.sqlite
brickbreaker/sound.py
brickbreaker/timer.py
brickbreaker/util.py
brickbreaker/assets/jingles/game_complete.ogg
brickbreaker/assets/jingles/game_over.ogg
brickbreaker/assets/jingles/level_complete.ogg
brickbreaker/assets/level_0/background.png
brickbreaker/assets/level_0/soundtrack.ogg
brickbreaker/assets/level_0/soundtrack_intro.ogg
brickbreaker/assets/level_1/background.png
brickbreaker/assets/level_1/soundtrack.ogg
brickbreaker/assets/level_2/background.png
brickbreaker/assets/level_2/soundtrack.ogg
brickbreaker/assets/level_3/background.png
brickbreaker/assets/level_3/soundtrack.ogg
brickbreaker/assets/level_3/soundtrack_intro.ogg
brickbreaker/assets/se/block_explode.ogg
brickbreaker/assets/se/lose_ball.ogg
brickbreaker/assets/se/lose_final_ball.ogg
brickbreaker/assets/se/paddle_wall_collide.ogg
brickbreaker/assets/sprites/ball.gif
brickbreaker/assets/sprites/bluepaddle.png
brickbreaker/assets/sprites/brownpaddle.png
brickbreaker-0.0.8.dist-info/LICENSE.txt
brickbreaker-0.0.8.dist-info/METADATA
brickbreaker-0.0.8.dist-info/WHEEL
brickbreaker-0.0.8.dist-info/entry_points.txt
brickbreaker-0.0.8.dist-info/top_level.txt
brickbreaker-0.0.8.dist-info/RECORD
